tbomb/.version
tbomb/__init__.py
tbomb/apidata.json
tbomb/bomber.py
tbomb/isdcodes.json
tbomb/utils/__init__.py
tbomb/utils/decorators.py
tbomb/utils/provider.py
tbomb-2.1.2.dist-info/LICENSE
tbomb-2.1.2.dist-info/METADATA
tbomb-2.1.2.dist-info/WHEEL
tbomb-2.1.2.dist-info/entry_points.txt
tbomb-2.1.2.dist-info/top_level.txt
tbomb-2.1.2.dist-info/RECORD
