Metadata-Version: 2.1
Name: tbomb
Version: 2.1.2
Summary: A free and open-source SMS,Call & Mail bombing application
Home-page: https://github.com/TheSpeedX/TBomb
Author: TheSpeedX
Author-email: ggspeedx29@gmail.com
License: GPL
Download-URL: https://github.com/TheSpeedX/TBomb/archive/pypi.zip
Keywords: android,spam,sms,mail,tbomb,call,bomb,termux,bomber,spammer
Platform: UNKNOWN
Classifier: Development Status :: 4 - Beta
Classifier: Intended Audience :: Developers
Classifier: Topic :: Software Development :: Libraries :: Python Modules
Classifier: License :: OSI Approved :: GNU General Public License v3 (GPLv3)
Classifier: Programming Language :: Python :: 3
Classifier: Operating System :: OS Independent
Classifier: Environment :: Console
Requires-Python: >=3.5
Requires-Dist: certifi (>=2020.6.20)
Requires-Dist: chardet (>=3.0.4)
Requires-Dist: colorama (>=0.4.3)
Requires-Dist: idna (>=2.10)
Requires-Dist: requests (>=2.24.0)
